tensors/__init__.py
tensors/indexed.py
tensor_algebra_dont_use-0.0.1.dist-info/METADATA
tensor_algebra_dont_use-0.0.1.dist-info/WHEEL
tensor_algebra_dont_use-0.0.1.dist-info/top_level.txt
tensor_algebra_dont_use-0.0.1.dist-info/RECORD
